ssc2ce_cpp.cpython-38-x86_64-linux-gnu.so
ssc2ce_cpp-0.3.0.dist-info/LICENSE
ssc2ce_cpp-0.3.0.dist-info/METADATA
ssc2ce_cpp-0.3.0.dist-info/WHEEL
ssc2ce_cpp-0.3.0.dist-info/top_level.txt
ssc2ce_cpp-0.3.0.dist-info/RECORD
