Metadata-Version: 2.1
Name: ssc2ce-cpp
Version: 0.3.0
Summary: A set of C++ parsers for ssc2ce
Home-page: UNKNOWN
Author: Oleg Nedbaylo
Author-email: olned64@gmail.com
License: UNKNOWN
Platform: UNKNOWN
